<annotation>
	<folder>Mako la buena</folder>
	<filename>Mako (70).jpg</filename>
	<path>C:\Users\Samuel\Desktop\Mako la buena\Mako (70).jpg</path>
	<source>
		<database>Unknown</database>
	</source>
	<size>
		<width>922</width>
		<height>616</height>
		<depth>3</depth>
	</size>
	<segmented>0</segmented>
	<object>
		<name>Mako</name>
		<pose>Unspecified</pose>
		<truncated>0</truncated>
		<difficult>0</difficult>
		<bndbox>
			<xmin>451</xmin>
			<ymin>206</ymin>
			<xmax>633</xmax>
			<ymax>299</ymax>
		</bndbox>
	</object>
</annotation>
